LICENSE
README.md
pyproject.toml
pyboot/components/netty/__init__.py
pyboot/components/netty/bootstrap.py
pyboot/components/netty/channel.py
pyboot/components/netty/codec.py
pyboot/components/netty/handler.py
pyboot/components/netty/server.py
pyboot_components_netty.egg-info/PKG-INFO
pyboot_components_netty.egg-info/SOURCES.txt
pyboot_components_netty.egg-info/dependency_links.txt
pyboot_components_netty.egg-info/entry_points.txt
pyboot_components_netty.egg-info/requires.txt
pyboot_components_netty.egg-info/top_level.txt
test/test_bootstrap.py
test/test_client.py