Metadata-Version: 2.4
Name: pyboot-components-netty
Version: 1.3.4
Summary: pyboot-components-netty is an open-source utility package that simplifies the development of async.
Author-email: joinsunsoft <793875613@qq.com>
Maintainer-email: joinsunsoft <inthirties.liu@hotmail.com>
License-Expression: Apache-2.0
Project-URL: Homepage, https://github.com/python-boot/commons-async
Project-URL: Repository, https://github.com/python-boot/commons-async
Project-URL: Issues, https://github.com/python-boot/commons-async
Keywords: netty,framework,cli,springboot,fastapi,netty
Classifier: Development Status :: 4 - Beta
Classifier: Intended Audience :: Developers
Classifier: Operating System :: OS Independent
Classifier: Programming Language :: Python :: 3
Classifier: Programming Language :: Python :: 3.8
Classifier: Programming Language :: Python :: 3.9
Classifier: Programming Language :: Python :: 3.10
Classifier: Programming Language :: Python :: 3.11
Classifier: Programming Language :: Python :: 3.12
Classifier: Topic :: Software Development :: Libraries :: Application Frameworks
Requires-Python: >=3.12.10
License-File: LICENSE
Requires-Dist: pyboot-commons-coroutine
Dynamic: license-file
